Metadata-Version: 2.1
Name: trans-tool
Version: 2.5.4
Summary: The translation files checker and syncing tool.
Home-page: https://github.com/MarcinOrlowski/trans-tool/
Author: Marcin Orlowski
Author-email: mail@marcinOrlowski.com
License: MIT License
Project-URL: Bug Tracker, https://github.com/MarcinOrlowski/trans-tool/issues/
Project-URL: Documentation, https://github.com/MarcinOrlowski/trans-tool/
Project-URL: Source Code, https://github.com/MarcinOrlowski/trans-tool/
Keywords: translation helper locale language sync check validation
Classifier: Programming Language :: Python :: 3
Classifier: License :: OSI Approved :: MIT License
Classifier: Operating System :: OS Independent
Requires-Python: >=3.6
License-File: LICENSE.md
Requires-Dist: argparse>=1.4.0
